AUTHORS.rst
CONTRIBUTING.rst
HISTORY.rst
LICENSE
MANIFEST.in
README.rst
setup.cfg
setup.py
docs/Makefile
docs/authors.rst
docs/conf.py
docs/contributing.rst
docs/history.rst
docs/index.rst
docs/installation.rst
docs/make.bat
docs/readme.rst
docs/usage.rst
rip/__init__.py
rip/api.py
rip/api_schema.py
rip/attribute_getter.py
rip/datetime_converter.py
rip/error_types.py
rip/filter_operators.py
rip/pipeline_composer.py
rip/request.py
rip/response.py
rip/url_constructor.py
rip.egg-info/PKG-INFO
rip.egg-info/SOURCES.txt
rip.egg-info/dependency_links.txt
rip.egg-info/not-zip-safe
rip.egg-info/requires.txt
rip.egg-info/top_level.txt
rip/crud/__init__.py
rip/crud/crud_actions.py
rip/crud/crud_pipeline_factory.py
rip/crud/crud_resource.py
rip/crud/tests.py
rip/django_adapter/__init__.py
rip/django_adapter/action_resolver.py
rip/django_adapter/api_request_builder.py
rip/django_adapter/django_http_handler.py
rip/django_adapter/django_response_builder.py
rip/django_adapter/metadata_factory.py
rip/django_adapter/tests.py
rip/generic_steps/__init__.py
rip/generic_steps/default_authentication.py
rip/generic_steps/default_authorization.py
rip/generic_steps/default_data_cleaner.py
rip/generic_steps/default_entity_actions.py
rip/generic_steps/default_post_action_hooks.py
rip/generic_steps/default_request_params_validation.py
rip/generic_steps/default_response_converter.py
rip/generic_steps/default_schema_serializer.py
rip/generic_steps/default_schema_validation.py
rip/generic_steps/tests.py
rip/schema/__init__.py
rip/schema/base_field.py
rip/schema/boolean_field.py
rip/schema/datetime_field.py
rip/schema/default_field_value.py
rip/schema/email_field.py
rip/schema/fields.py
rip/schema/float_field.py
rip/schema/id_field.py
rip/schema/integer_field.py
rip/schema/list_field.py
rip/schema/list_sub_resource_field.py
rip/schema/resource_link_field.py
rip/schema/resource_uri_field.py
rip/schema/schema_field.py
rip/schema/string_field.py
rip/schema/sub_resource_field.py
rip/schema/tests.py
rip/schema/validation_result.py
tests/__init__.py
tests/request_factory.py
tests/test_settings.py
tests/integration_tests/__init__.py
