Metadata-Version: 1.1
Name: rip
Version: 0.0.1
Summary: A python framework for writing restful APIs.
Home-page: https://github.com/aplopio/rip
Author: Aplopio developers
Author-email: devs@aplopio.com
License: MIT
Keywords: rip
Platform: UNKNOWN
Classifier: Development Status :: 2 - Pre-Alpha
Classifier: Intended Audience :: Developers
Classifier: License :: OSI Approved :: BSD License
Classifier: Natural Language :: English
Classifier: Programming Language :: Python :: 2.7
